{
	"info": {
		"_postman_id": "768b75a8-6a8b-4446-8b69-63de063b35a4",
		"name": "Senai.Rental.Manha",
		"schema": "https://schema.getpostman.com/json/collection/v2.1.0/collection.json"
	},
	"item": [
		{
			"name": "Clientes",
			"item": [
				{
					"name": "Cliente.Cadastrar",
					"request": {
						"method": "POST",
						"header": [],
						"body": {
							"mode": "raw",
							"raw": "{\r\n    \"NomeCliente\" : \"Pedro\",\r\n    \"SobrenomeCliente\" : \"Santos\",\r\n    \"CPF\" : \"13345627123\",\r\n    \"DataNascimento\" : \"2003-06-27\"\r\n}",
							"options": {
								"raw": {
									"language": "json"
								}
							}
						},
						"url": {
							"raw": "http://localhost:5000/api/clientes",
							"protocol": "http",
							"host": [
								"localhost"
							],
							"port": "5000",
							"path": [
								"api",
								"clientes"
							]
						}
					},
					"response": []
				},
				{
					"name": "Cliente.BuscarPorId",
					"request": {
						"method": "GET",
						"header": [],
						"url": {
							"raw": "http://localhost:5000/api/clientes/5",
							"protocol": "http",
							"host": [
								"localhost"
							],
							"port": "5000",
							"path": [
								"api",
								"clientes",
								"5"
							]
						}
					},
					"response": []
				},
				{
					"name": "Cliente.Deletar",
					"request": {
						"method": "DELETE",
						"header": [],
						"url": {
							"raw": "http://localhost:5000/api/clientes/1",
							"protocol": "http",
							"host": [
								"localhost"
							],
							"port": "5000",
							"path": [
								"api",
								"clientes",
								"1"
							]
						}
					},
					"response": []
				},
				{
					"name": "Cliente.ListarTodos",
					"request": {
						"method": "GET",
						"header": [],
						"url": {
							"raw": "http://localhost:5000/api/clientes",
							"protocol": "http",
							"host": [
								"localhost"
							],
							"port": "5000",
							"path": [
								"api",
								"clientes"
							]
						}
					},
					"response": []
				}
			]
		},
		{
			"name": "Alugueis",
			"item": [
				{
					"name": "Aluguel.Cadastrar",
					"request": {
						"method": "POST",
						"header": [],
						"body": {
							"mode": "raw",
							"raw": "{\r\n    \"IdCliente\" : 5,\r\n    \"IdVeiculo\" : 3,\r\n    \"Preco\" : 700,\r\n    \"Data\" : \"2020-06-06\"\r\n   \r\n}",
							"options": {
								"raw": {
									"language": "json"
								}
							}
						},
						"url": {
							"raw": "http://localhost:5000/api/alugueis",
							"protocol": "http",
							"host": [
								"localhost"
							],
							"port": "5000",
							"path": [
								"api",
								"alugueis"
							]
						}
					},
					"response": []
				},
				{
					"name": "Aluguel.BuscarPorId",
					"request": {
						"method": "GET",
						"header": [],
						"url": {
							"raw": "http://localhost:5000/api/alugueis/10",
							"protocol": "http",
							"host": [
								"localhost"
							],
							"port": "5000",
							"path": [
								"api",
								"alugueis",
								"10"
							]
						}
					},
					"response": []
				},
				{
					"name": "Aluguel.Deletar",
					"request": {
						"method": "DELETE",
						"header": [],
						"url": {
							"raw": "http://localhost:5000/api/alugueis/11",
							"protocol": "http",
							"host": [
								"localhost"
							],
							"port": "5000",
							"path": [
								"api",
								"alugueis",
								"11"
							]
						}
					},
					"response": []
				},
				{
					"name": "Aluguel.ListarTodos",
					"request": {
						"method": "GET",
						"header": [],
						"url": {
							"raw": "http://localhost:5000/api/alugueis",
							"protocol": "http",
							"host": [
								"localhost"
							],
							"port": "5000",
							"path": [
								"api",
								"alugueis"
							]
						}
					},
					"response": []
				}
			]
		},
		{
			"name": "Veiculos",
			"item": [
				{
					"name": "Veiculo.Cadastrar",
					"request": {
						"method": "POST",
						"header": [],
						"body": {
							"mode": "raw",
							"raw": "{\r\n     \"IdEmpresa\" : 1,\r\n    \"Placa\" : \"444\",\r\n    \"IdModelo\" : 2\r\n}",
							"options": {
								"raw": {
									"language": "json"
								}
							}
						},
						"url": {
							"raw": "http://localhost:5000/api/veiculos",
							"protocol": "http",
							"host": [
								"localhost"
							],
							"port": "5000",
							"path": [
								"api",
								"veiculos"
							]
						}
					},
					"response": []
				},
				{
					"name": "Veiculo.BuscarPorId",
					"request": {
						"method": "GET",
						"header": [],
						"url": {
							"raw": "http://localhost:5000/api/veiculos/5",
							"protocol": "http",
							"host": [
								"localhost"
							],
							"port": "5000",
							"path": [
								"api",
								"veiculos",
								"5"
							]
						}
					},
					"response": []
				},
				{
					"name": "Veiculo.Deletar",
					"request": {
						"method": "DELETE",
						"header": [],
						"url": {
							"raw": "http://localhost:5000/api/veiculos/6",
							"protocol": "http",
							"host": [
								"localhost"
							],
							"port": "5000",
							"path": [
								"api",
								"veiculos",
								"6"
							]
						}
					},
					"response": []
				},
				{
					"name": "Veiculo.ListarTodos",
					"request": {
						"method": "GET",
						"header": [],
						"url": {
							"raw": "http://localhost:5000/api/veiculos",
							"protocol": "http",
							"host": [
								"localhost"
							],
							"port": "5000",
							"path": [
								"api",
								"veiculos"
							]
						}
					},
					"response": []
				}
			]
		}
	]
}